intobot/__main__.py
intobot-0.1.1.dist-info/LICENSE
intobot-0.1.1.dist-info/WHEEL
intobot-0.1.1.dist-info/METADATA
intobot-0.1.1.dist-info/RECORD
