Metadata-Version: 2.1
Name: intobot
Version: 0.1.1
Summary: A tool to make every script into a VK bot. Better than `every_script_is_a_vk_bot`, because `intobot` can serve multiple users simultaneously.
License: MIT
Author: megahomyak
Author-email: g.megahomyak@gmail.com
Requires-Python: >=3.7.2,<4.0.0
Classifier: License :: OSI Approved :: MIT License
Classifier: Programming Language :: Python :: 3
Classifier: Programming Language :: Python :: 3.8
Classifier: Programming Language :: Python :: 3.9
Classifier: Programming Language :: Python :: 3.10
Classifier: Programming Language :: Python :: 3.11
Requires-Dist: loguru (>=0.6.0,<0.7.0)
Requires-Dist: vkbottle (>=4.3.12,<5.0.0)
